{
  "NWF_Symmetric": {
    "precision_at_k": 0.83984375,
    "bytes_per_obj": 512,
    "compression_ratio": 1.53125
  },
  "NWF_Euclidean": {
    "precision_at_k": 0.84375,
    "bytes_per_obj": 512,
    "compression_ratio": 1.53125
  },
  "FAISS_L2": {
    "precision_at_k": 0.84375,
    "bytes_per_obj": 256,
    "compression_ratio": 3.0625
  },
  "HDC": {
    "precision_at_k": 0.8515625,
    "bytes_per_obj": 250,
    "compression_ratio": 3.136
  },
  "_meta": {
    "n_indexed": 512,
    "n_test": 200,
    "k": 10,
    "use_kalman": false,
    "metric": "symmetric"
  }
}